CHANGES.txt
MANIFEST.in
README.txt
fixeol.py
setup.py
eolfixer.egg-info/PKG-INFO
eolfixer.egg-info/SOURCES.txt
eolfixer.egg-info/dependency_links.txt
eolfixer.egg-info/entry_points.txt
eolfixer.egg-info/namespace_packages.txt
eolfixer.egg-info/not-zip-safe
eolfixer.egg-info/requires.txt
eolfixer.egg-info/top_level.txt