Metadata-Version: 1.0
Name: eolfixer
Version: 1.1
Summary: Reinout's installable copy of pypy's fixeol script
Home-page: http://bitbucket.org/reinout/eolfixer
Author: Reinout van Rees
Author-email: reinout@vanrees.org
License: MIT
Platform: UNKNOWN
Classifier: Development Status :: 5 - Production/Stable
Classifier: Environment :: Console
Classifier: Intended Audience :: Developers
Classifier: License :: OSI Approved :: MIT License
Classifier: Programming Language :: Python
Classifier: Topic :: Software Development :: Quality Assurance
Classifier: Topic :: Utilities
